tex2tree/__init__.py
tex2tree/dictionary.txt
tex2tree/label_graph.py
tex2tree/parser.out
tex2tree/parsetab.py
tex2tree/tex_lex.py
tex2tree/tex_parser.py
tex2tree-0.1.0.dist-info/WHEEL
tex2tree-0.1.0.dist-info/METADATA
tex2tree-0.1.0.dist-info/RECORD
